var_process/__init__.py
var_process/collector/__init__.py
var_process/collector/var_collector.py
var_process/functional/__init__.py
var_process/functional/on_error.py
var_process/saver/__init__.py
var_process/saver/var_saver.py
var_process/utils/__init__.py
var_process/utils/save_policy.py
var_process-0.0.1.dist-info/METADATA
var_process-0.0.1.dist-info/WHEEL
var_process-0.0.1.dist-info/top_level.txt
var_process-0.0.1.dist-info/RECORD
