Metadata-Version: 2.1
Name: var_process
Version: 0.0.1
Summary: Auto process vars in your pipeline.
Home-page: https://github.com/Yu-Jie1669/checkpointer
Author: Yj Lin
Author-email: yjlin2001@gmail.com
Classifier: Programming Language :: Python :: 3
Classifier: License :: OSI Approved :: MIT License
Classifier: Operating System :: OS Independent
Requires-Python: >=3.6
Requires-Dist: numpy
Requires-Dist: torch
